ovoenergy/__init__.py
ovoenergy/__main__.py
ovoenergy/const.py
ovoenergy/exceptions.py
ovoenergy/models/__init__.py
ovoenergy/models/accounts.py
ovoenergy/models/carbon_intensity.py
ovoenergy/models/footprint.py
ovoenergy/models/oauth.py
ovoenergy/models/plan.py
ovoenergy-3.0.1.dist-info/licenses/LICENSE
ovoenergy-3.0.1.dist-info/METADATA
ovoenergy-3.0.1.dist-info/WHEEL
ovoenergy-3.0.1.dist-info/top_level.txt
ovoenergy-3.0.1.dist-info/RECORD
