Metadata-Version: 2.4
Name: ovoenergy
Version: 3.0.1
Summary: OVO Energy
Home-page: https://github.com/timmo001/ovoenergy
Author: Aidan Timson (Timmo)
Author-email: aidan@timmo.dev
License: Apache-2.0
Keywords: python,ovoenergy,api
Requires-Python: >=3.11
License-File: LICENSE
Requires-Dist: aiohttp>=3.8.5; python_version < "3.12"
Requires-Dist: aiohttp>=3.9.0b0; python_version >= "3.12"
Requires-Dist: typer>=0.6.1
Requires-Dist: PyJWT>=2.0.0
Dynamic: author
Dynamic: author-email
Dynamic: description
Dynamic: description-content-type
Dynamic: home-page
Dynamic: keywords
Dynamic: license
Dynamic: license-file
Dynamic: requires-dist
Dynamic: requires-python
Dynamic: summary
